webid/__init__.py
pywebid-0.0.2.dist-info/LICENSE
pywebid-0.0.2.dist-info/WHEEL
pywebid-0.0.2.dist-info/METADATA
pywebid-0.0.2.dist-info/RECORD
