Metadata-Version: 2.1
Name: pywebid
Version: 0.0.2
Summary: This module provides a WebID implementation.
Author-email: Kushal Das <mail@kushaldas.in>
Requires-Python: >=3.6
Classifier: Development Status :: 3 - Alpha
Classifier: Programming Language :: Python :: 3
Classifier: Topic :: Software Development :: Libraries :: Python Modules
Classifier: License :: OSI Approved :: MIT License
Requires-Dist: rdflib
Project-URL: Documentation, https://webid.readthedocs.io/en/latest/
Project-URL: Source, https://github.com/projectliquid/webid
